MANIFEST.in
setup.py
penguin/__init__.py
penguin/structs.py
penguin.egg-info/PKG-INFO
penguin.egg-info/SOURCES.txt
penguin.egg-info/dependency_links.txt
penguin.egg-info/top_level.txt
src/common.h
src/fds.c
src/linux_kaio.c
src/posix_aio.c
src/posix_ipc.c
src/signals.c
src/sysv_ipc.c
src/missing-headers/libaio.h
src/missing-headers/sys/eventfd.h
src/missing-headers/sys/inotify.h
src/missing-headers/sys/signalfd.h
src/missing-headers/sys/timerfd.h