Metadata-Version: 1.0
Name: penguin
Version: 0.2.4
Summary: bindings to additional linux syscalls and C libraries
Home-page: UNKNOWN
Author: Travis Parker
Author-email: travis.parker@gmail.com
License: UNKNOWN
Platform: UNKNOWN
